{"name":"index_b5a75592bf864d49fae1","content":{"./src/bootstrap.js":{"id":7,"meta":{"harmonyModule":true},"exports":["default"]},"./src/router/index.js":{"id":32,"meta":{"harmonyModule":true},"exports":["default"]},"./src/entries/index/index.js":{"id":48,"meta":{"harmonyModule":true},"exports":[]},"./src/entries/index/view/index.vue":{"id":87,"meta":{}},"./node_modules/babel-loader/lib/index.js!./node_modules/vue-loader/lib/selector.js?type=script&index=0!./src/entries/index/view/index.vue":{"id":88,"meta":{"harmonyModule":true},"exports":["default"]},"./node_modules/vue-loader/lib/template-compiler/index.js?{\"id\":\"data-v-4a7884e0\"}!./node_modules/vue-loader/lib/selector.js?type=template&index=0!./src/entries/index/view/index.vue":{"id":89,"meta":{}},"./src/assets/css/public.css":{"id":90,"meta":{}}}}